json_de2zh/__init__.py
json_de2zh/__main__.py
json_de2zh/de2zh.py
json_de2zh/fundset.lzma
json_de2zh/gen_cmat.py
json_de2zh/lemma_split.py-
json_de2zh/split_compound.py
json_de2zh-0.1.1.dist-info/entry_points.txt
json_de2zh-0.1.1.dist-info/LICENSE
json_de2zh-0.1.1.dist-info/WHEEL
json_de2zh-0.1.1.dist-info/METADATA
json_de2zh-0.1.1.dist-info/RECORD
